README.md
setup.py
Flask_Helper.egg-info/PKG-INFO
Flask_Helper.egg-info/SOURCES.txt
Flask_Helper.egg-info/dependency_links.txt
Flask_Helper.egg-info/requires.txt
Flask_Helper.egg-info/top_level.txt
flask_helper/__init__.py
flask_helper/_flask.py
flask_helper/ctx.py
flask_helper/exception.py
flask_helper/flask2.py
flask_helper/flask_hook.py
flask_helper/globals.py
flask_helper/sessions.py
flask_helper/template.py
flask_helper/upload.py
flask_helper/url_rule.py
flask_helper/view.py
flask_helper/hooks/__init__.py
flask_helper/hooks/cors_hook.py
flask_helper/hooks/handle_30x_hook.py
flask_helper/hooks/real_ip_hook.py
flask_helper/hooks/request_id_hook.py
flask_helper/hooks/user_agent_hook.py
flask_helper/utils/__init__.py
flask_helper/utils/folder.py
flask_helper/utils/ip.py
flask_helper/utils/loader.py
flask_helper/utils/log.py
flask_helper/utils/registry.py