Metadata-Version: 1.0
Name: Flask-Helper
Version: 2.1.1
Summary: Flask Helper
Home-page: https://github.com/meisanggou/Flask-Helper
Author: meisanggou
Author-email: zhou5315938@163.com
License: MIT
Keywords: flask_helper
Platform: UNKNOWN
